d2lvalence/__init__.py
d2lvalence/auth.py
d2lvalence-1.2.3.dist-info/LICENSE
d2lvalence-1.2.3.dist-info/METADATA
d2lvalence-1.2.3.dist-info/WHEEL
d2lvalence-1.2.3.dist-info/top_level.txt
d2lvalence-1.2.3.dist-info/RECORD
